{"video_id": 10966040, "first_message_time": "2025-12-29 11:00:01 +0900", "events": [{"event": {"start_sec": 382, "end_sec": 406, "peak_sec": 391, "peak_z_score": 11.309907731493658, "peak_count": 6}, "evidence": "군용침대 훔쳐옵시다 | 허츄님 안녕하세용♡♡ | 하나는 앞뒤로 젖히는거 | 허리아파서 어캐씀? | 바보..", "summary": "허츄가 허리 아파하는 상황에서 누워보거나 침대 사용법을 이제 깨달았다는 놀림과 장난 섞인 반응이 쏟아진다.", "title": "허츄 허리통증에 침대 사용법 깨달음 폭소"}, {"event": {"start_sec": 800, "end_sec": 807, "peak_sec": 802, "peak_z_score": 9.173717637424497, "peak_count": 6}, "evidence": "허츄님이 사회? | 사회요? | 이분 쓰러져.. | mc잘하긴해", "summary": "허츄님이 사회를 맡자 놀라며 쓰러지는 반응이 터졌다.", "title": "허츄님 MC 발탁에 충격과 쓰러짐 대란"}, {"event": {"start_sec": 926, "end_sec": 938, "peak_sec": 931, "peak_z_score": 10.853564953350986, "peak_count": 5}, "evidence": "쌀먹교수 | 교수님 저격 | 수업 쌀먹ㄷㄷ | 날먹 인죵 | 발표수업 날먹", "summary": "교수님의 수업이 쌀먹 수준이라며 날먹 인생이라고 놀리며 저격하는 분위기.", "title": "쌀먹 교수님 수업 날먹 저격 대란"}, {"event": {"start_sec": 3226, "end_sec": 3234, "peak_sec": 3228, "peak_z_score": 8.938365665621228, "peak_count": 5}, "evidence": "개웃기네 ㅋㅋ | 억빠 ㄴ | 허츄는 더이상 순딩순딩 아니다 | 미쳣나봐..", "summary": "허츄가 더이상 순딩순딩이 아니라고 하며 미쳤나봐라고 웃으며 반응하는 상황.", "title": "허츄 순딩순딩 끝! 미쳤나봐 폭발ㅋㅋ"}, {"event": {"start_sec": 3374, "end_sec": 3393, "peak_sec": 3378, "peak_z_score": 12.269560352739303, "peak_count": 6}, "evidence": "허츄없는 단톡방 | 츄없톡 | 허츄 가엽서ㅠㅠ | 골댕이처럼", "summary": "'허츄'가 친구들 단톡방에서 제외되어 버려진 듯한 상황에 시청자들이 동정하며 놀림.", "title": "허츄, 단톡방에서 버려진 가엾은 존재ㅠㅠ"}, {"event": {"start_sec": 4185, "end_sec": 4202, "peak_sec": 4188, "peak_z_score": 10.958609621479214, "peak_count": 9}, "evidence": "스펠렁키 | 허츄 | 츄쪽 | 룽키 | 생존게임", "summary": "스펠렁키와 허츄, 츄쪽 중 대표를 두고 의견이 갈리며 룽키 퇴장과 생존게임 제안을 논의 중이다.", "title": "츄쪽 vs 허츄 대표 논쟁에 룽키 ㅂㅂ?"}, {"event": {"start_sec": 4272, "end_sec": 4309, "peak_sec": 4279, "peak_z_score": 15.0459890702967, "peak_count": 9}, "evidence": "질투질투 ㅋㅋ | 질척질척 | 얼른 쉬어", "summary": "누군가 몸이 안 좋다고 하자 시청자들이 질척거리며 질투 타령하고 얼른 쉬라고 재촉한다.", "title": "질척이는 팬들, 쉬라고 재촉하는 피크 채팅"}, {"event": {"start_sec": 5434, "end_sec": 5453, "peak_sec": 5442, "peak_z_score": 13.763096338338086, "peak_count": 12}, "evidence": "츄바 | 가라 | 도발하지마 | 가세요라 | 누구냐", "summary": "츄바가 안 가고 질척거리며 도발해 모두가 가라고 소리치고 누구냐 물으며 쳐내려 함.", "title": "츄바 안 간다며 도발하는 상황에 화난 리액션 폭발"}, {"event": {"start_sec": 5475, "end_sec": 5541, "peak_sec": 5484, "peak_z_score": 8.742816312441526, "peak_count": 6}, "evidence": "츄바츄바 | 푹 쉬고 | 가라 | 몸살약 | 올데이", "summary": "허츄가 몸살로 아파서 푹 쉬라는 츄바츄바 응원 속에 방송을 끝내고 가라는 시청자들이 재촉하며 수요일 올데이 일정 걱정.", "title": "허츄 몸살로 츄바 응원 속 조기 퇴장 위기"}]}