{"video_id": 10989270, "first_message_time": "2025-12-30 20:01:35 +0900", "events": [{"event": {"start_sec": 37, "end_sec": 84, "peak_sec": 65, "peak_z_score": 22.181912057738835, "peak_count": 3}, "evidence": "반갑나나 | 나나가 와써 | 방제 너무 설레네 | 나나가 왔써", "summary": "시청자들이 \"나나\"의 등장과 설레는 방제에 \"반갑나나\"라고 열광적으로 환영하며 축하한다.", "title": "나나 등장에 팬들 '반갑나나' 열광 폭발!"}, {"event": {"start_sec": 182, "end_sec": 243, "peak_sec": 208, "peak_z_score": 17.8957827392193, "peak_count": 23}, "evidence": "반갑나나 | 왜 기분좋아? | 아이고 | 그치 | 녹음 잘했어?", "summary": "나나가 기분 좋아 보이는 모습에 모두가 반갑게 맞이하다가 갑자기 안 좋은 일이 생겨 아이고 소리와 그치 반응이 쏟아짐.", "title": "나나 등장 환호 속 충격 소식 터져 '아이고' 폭발!"}, {"event": {"start_sec": 2169, "end_sec": 2200, "peak_sec": 2191, "peak_z_score": 10.335103057683217, "peak_count": 20}, "evidence": "내 사투리 | 사투리 돌려줘 | 블루베리스무디 | 안대 | 플러팅 ㄷㄷ", "summary": "나나가 사투리를 안 쓰겠다고 도전하지만 계속 실패하며 시청자들이 사투리 돌려주라고 재촉하는 상황.", "title": "나나 사투리 금지 도전, 3분도 못 버티는 실패기"}, {"event": {"start_sec": 3065, "end_sec": 3098, "peak_sec": 3082, "peak_z_score": 9.255333071920937, "peak_count": 18}, "evidence": "나나야 | 증나나 | 성 떼면 고백 | ㄹㅇㅋㅋ | 성 붙이면안됨", "summary": "시청자들이 '나나야', '증나나'처럼 성을 떼고 부르는 게 플러팅이나 고백 신호라며 '성 떼면 고백' 규칙을 농담으로 과장하며 반복 장난.", "title": "성 떼고 부르면 고백? 나나야 열풍 터진 채팅"}, {"event": {"start_sec": 3741, "end_sec": 3769, "peak_sec": 3744, "peak_z_score": 8.452836804862335, "peak_count": 14}, "evidence": "나나야 | 설래지마라 | 플러팅 아니다 | 페토야 | 이름은 원래 부르는거야", "summary": "누군가 '나나야'나 '페토야'처럼 이름을 다정하게 불러주자 시청자들이 플러팅이나 설렘으로 착각하며 \"설래지마라\" \"플러팅 아니다\"로 부정하며 놀리는 상황.", "title": "이름 불렀다고 설레는 바보들ㅋㅋ 플러팅 아냐!"}, {"event": {"start_sec": 5982, "end_sec": 5992, "peak_sec": 5986, "peak_z_score": 8.007148161549237, "peak_count": 18}, "evidence": "너 잘걸렸다 | 바로 납치 | 타겟이 제발로 들어왔따 | 스스로 걸어 들어왔구만", "summary": "타겟이 스스로 걸어 들어와 납치 대신 바로 모셔오기로 흥분된 반응이 쏟아짐.", "title": "타겟 제 발로 납치당해! 바로 모셔오기 대박"}, {"event": {"start_sec": 7616, "end_sec": 7629, "peak_sec": 7622, "peak_z_score": 9.478757387189027, "peak_count": 18}, "evidence": "70~80 | 키-100 | 키빼몸 100 | 키 -110 | 70대", "summary": "사람들이 키에서 100~110을 빼거나 70~80 사이 수치를 추측하며 이상적인 몸무게를 논의한다.", "title": "이상적 몸무게, 키-100~110으로 70대?"}, {"event": {"start_sec": 7796, "end_sec": 7822, "peak_sec": 7799, "peak_z_score": 9.04367782951262, "peak_count": 21}, "evidence": "오.. | 퍽퍽 | 단단한소리 | 갈라져? | 탄탄한데", "summary": "누군가의 허벅지를 만지며 퍽퍽 두드리니 단단한소리와 둔탁한 탄탄한데 소리가 나서 모두 놀라며 근육을 감탄한다.", "title": "허벅지 퍽퍽 치니 둔탁한 근육소리 터짐"}, {"event": {"start_sec": 7876, "end_sec": 7904, "peak_sec": 7895, "peak_z_score": 11.435621188109218, "peak_count": 20}, "evidence": "엥 입었어? | 벗어..? | 벗어주세요..! | 우효wwwwwwwwwwwwwwwwwwwwwwwwwwwwwwwwwwwwwwww | 페평", "summary": "누군가 갑자기 옷을 입었다가 벗으면서 \"우효\" 소리와 \"페평\" 논란이 터진 상황.", "title": "갑작스런 입고→벗기 이벤트에 우효 폭발! 페평 위기"}, {"event": {"start_sec": 8085, "end_sec": 8108, "peak_sec": 8097, "peak_z_score": 9.963117943376206, "peak_count": 23}, "evidence": "분해요? | 조립식이야? | 팬티가 분해 | 심리스가 그런게 | 접착부위 떨어져서", "summary": "누군가 팬티가 건조기에서 '분해'된 충격적인 경험담을 공유해 모두가 '분해요?' '조립식이야?' 하며 놀라워한다.", "title": "팬티 건조기 분해 쇼크! 조립식 의심 폭발"}, {"event": {"start_sec": 9825, "end_sec": 9842, "peak_sec": 9833, "peak_z_score": 8.895521719899406, "peak_count": 25}, "evidence": "눅눅한 양배추 | 제습기 | 린은 왜 | 마신춤", "summary": "누군가 울어 눅눅한 양배추라고 놀리며 제습기 켜고 린은 왜 다른 반응 보이는 상황.", "title": "눅눅한 양배추 울음에 제습기 가동 린 혼자 딴짓"}, {"event": {"start_sec": 9899, "end_sec": 9914, "peak_sec": 9906, "peak_z_score": 8.145284191808061, "peak_count": 21}, "evidence": "제습기 | 위용위용 | 뇨 | 린은 왜 | 리벅지", "summary": "린 캐릭터에게 제습기·뇨·위용위용 소리만 나오고 리벅지도 실패해 시청자들이 놀라며 웃는 상황.", "title": "린 제습기만 뱉는 미스터리 사운드ㅋㅋ"}, {"event": {"start_sec": 9994, "end_sec": 10044, "peak_sec": 10034, "peak_z_score": 8.350494929972372, "peak_count": 24}, "evidence": "대 강 지 | 캬ㅑㅑㅑ | ㅡㅅㅡ | 눅눅해진다 | 휴지 뽑아", "summary": "감동적인 장면에 나나가 울음을 터뜨려 시청자들이 \"대 강 지\"와 \"눅눅해진다\" 하며 눈물과 휴지 소리에 공감하며 반응", "title": "나나 대감동 울음에 눈물방류 대란!"}, {"event": {"start_sec": 10856, "end_sec": 10877, "peak_sec": 10861, "peak_z_score": 11.1008717748439, "peak_count": 24}, "evidence": "면허 | 운전면허 커버 | 드라이버 라이센스 | 바빴다 | 내년에 따면돼", "summary": "올해 운전면허 따기 목표를 바빴다며 실패했지만, 드라이버 라이센스 커버곡으로 위로하며 내년을 기약한다.", "title": "올해 면허 실패, 드라이버 라이센스 커버로 축하!"}, {"event": {"start_sec": 10979, "end_sec": 10995, "peak_sec": 10984, "peak_z_score": 8.733229239480915, "peak_count": 19}, "evidence": "지구 2026살 | 문과지 | 크아악 | 기원전 | +46억", "summary": "지구 나이를 2026살로 착각하며 문과 놀림과 46억 년 실제 나이로 드립 치는 소동.", "title": "지구 2026살 문과 드립 폭발!"}, {"event": {"start_sec": 12175, "end_sec": 12190, "peak_sec": 12179, "peak_z_score": 8.31359014704256, "peak_count": 28}, "evidence": "고생했어 | 밥 무 | 수고했어 | 바이나나 | 녹음도 하고", "summary": "누군가 녹음도 하고 고생한 끝에 배고파서 밥 무러 가는 상황이다.", "title": "고생 끝! 배고파서 밥무 타임 온다"}]}