{"video_id": 10993567, "first_message_time": "2025-12-30 22:25:30 +0900", "events": [{"event": {"start_sec": 66, "end_sec": 76, "peak_sec": 70, "peak_z_score": 13.389014647213774, "peak_count": 9}, "evidence": "ㅔㅔ | 네 | 드디어 실시간 | 큐베는 같은팀이면 좋겠는데~ | 리하", "summary": "시청자들이 ㅔㅔ와 네로 열광하며 드디어 실시간 참여와 큐베 같은 팀, 리하를 언급한 상황.", "title": "실시간 풀린 순간 ㅔㅔ 폭발과 큐베팀 희망!"}, {"event": {"start_sec": 162, "end_sec": 183, "peak_sec": 167, "peak_z_score": 12.57324735306821, "peak_count": 9}, "evidence": "큐배가 다시 붙었어 | 우승! | 윤요? | 분탕받을듯 | 쇼핑리스트 팀이네요", "summary": "큐배가 다시 붙고 윤요 푸린이 합류해 쇼핑리스트 팀이 우승했지만 분탕과 트레이드 걱정이 쏟아진다.", "title": "큐베·윤요 쇼핑리스트 우승! 분탕 위기?"}, {"event": {"start_sec": 961, "end_sec": 984, "peak_sec": 972, "peak_z_score": 8.395688807292887, "peak_count": 7}, "evidence": "바꿈? | 푸린 바뀜? | 8팀은 뭐 왜 바꿀일있는데 | 4팀 13팀 왜 이럼 | 망했네", "summary": "8팀 선수가 푸린으로 바뀌었고 4팀 13팀도 변경되어 팀 조합이 엉망이 된 상황.", "title": "팀원 갑작스런 변경으로 초비상! 망한 조합"}, {"event": {"start_sec": 1435, "end_sec": 1468, "peak_sec": 1446, "peak_z_score": 13.26998290206339, "peak_count": 9}, "evidence": "분내팟 | 여자 3 | 푸순이 가자 | 4분내 | 꽃밭입니다", "summary": "팀원이 모두 여성으로 구성된 '분내팟'이 되어 푸린이 푸순이로 변장해 즐겜하자는 반응이 쏟아진다.", "title": "분내팟 완성! 푸순이 변신으로 꽃밭 가즈아"}, {"event": {"start_sec": 1605, "end_sec": 1620, "peak_sec": 1613, "peak_z_score": 9.738879357420611, "peak_count": 6}, "evidence": "조졌네 ㅋㅋ | 공겜 드가자 | 가방2 | 30시간이요..?? | 석이 그냥 지대로 나가노", "summary": "석이가 초보 실수로 30시간 걸린 가방2 상황에서 조져서 모두 공겜 즐겜으로 전환한다.", "title": "석이 뉴비 실수로 조져 공겜 즐겜 돌입!"}, {"event": {"start_sec": 2157, "end_sec": 2187, "peak_sec": 2174, "peak_z_score": 9.043136399834951, "peak_count": 8}, "evidence": "미르시치 | 미안해야지 | 책임져 | 코치해라 | 도와줘", "summary": "미르시치가 실수로 미안해야지 하며 책임져 달라는 채팅이 쏟아지고, 와서 코치해라고 요구한다.", "title": "미르 실수에 시청자들 사과와 코치 요구 폭발!"}, {"event": {"start_sec": 2267, "end_sec": 2293, "peak_sec": 2275, "peak_z_score": 8.722977865848023, "peak_count": 6}, "evidence": "샷 좋으신데 | 트레이드 굳 | 에임 좋고 | 베이팅 ㄷㄷ | ㄹㅇㅋㅋ", "summary": "상대를 상대로 에임 좋고 샷 좋으신데 트레이드 굳으로 베이팅하며 시원하게 교전 성공했다.", "title": "에임 샷 트레이드 굳! 베이팅 폭딜 승리ㅋㅋ"}, {"event": {"start_sec": 2376, "end_sec": 2395, "peak_sec": 2385, "peak_z_score": 8.625762386649662, "peak_count": 8}, "evidence": "미르시치 | 해야해 | 책임져 | 30시간은 무조건이지 | 미르다요", "summary": "시청자들이 미르시치에게 30시간은 무조건이지 연습을 책임지라고 강하게 요구하며 해야해 분위기를 띄우고 있다.", "title": "미르시치, 30시간 연습 책임져! 시청자 열광"}, {"event": {"start_sec": 3060, "end_sec": 3071, "peak_sec": 3063, "peak_z_score": 8.341542577321272, "peak_count": 6}, "evidence": "베릴 쏘는 거 | 대가리에 | 우크릭안하고 | ㄹㅈㄷ | 이맛이야", "summary": "베릴을 쏘자 대가리에 맞아 우크릭 안 하고 ㄹㅈㄷ로 웃음바다가 됐다.", "title": "베릴 대가리 직격으로 ㄹㅈㄷ 폭발!"}, {"event": {"start_sec": 3412, "end_sec": 3424, "peak_sec": 3417, "peak_z_score": 10.506527571244446, "peak_count": 4}, "evidence": "바람직해 | 인재상 | 8시간 더 할 수있다 | 야행성", "summary": "누군가 바람직하고 인재상처럼 야행성으로 8시간 더 할 수 있다는 반응이 쏟아진다.", "title": "야행성 인재상, 8시간 더 버틸 기세!"}, {"event": {"start_sec": 4275, "end_sec": 4295, "peak_sec": 4281, "peak_z_score": 14.879377403657324, "peak_count": 2}, "evidence": "ㄹㅇㅋㅋ | 맞지 | 이걸 못알아듣는다고? | 방어구", "summary": "누군가 \"방어구\"라는 말을 못 알아듣는다고 놀리며 다들 웃고 있다.", "title": "방어구 못 알아듣는 사람에 대한 폭소 리액션"}, {"event": {"start_sec": 4685, "end_sec": 4695, "peak_sec": 4690, "peak_z_score": 8.708463792170146, "peak_count": 3}, "evidence": "관전 | 관전으로 봐야해 | 관전 눌러 | 그 옆에 | 우리 안보이나?", "summary": "누군가 우리 안보인다고 하자 모두 그 옆에 관전 눌러야 한다고 안내하며 관전으로 봐야 한다고 깨닫는다.", "title": "관전 버튼 눌러야 우리 보인다! 깨달음 순간"}, {"event": {"start_sec": 4827, "end_sec": 4843, "peak_sec": 4828, "peak_z_score": 8.875537583915076, "peak_count": 3}, "evidence": "오? | 사이가 나이스 | 재능있숴 | 샷건으로 와", "summary": "누군가 기본적인 샷건 실력을 보이며 재능을 인정받고 사이가 좋다는 반응이 나왔다.", "title": "샷건 재능 인정받는 순간! 사이 나이스"}, {"event": {"start_sec": 4907, "end_sec": 4918, "peak_sec": 4909, "peak_z_score": 12.721268419235225, "peak_count": 2}, "evidence": "오옹 | 오? | 우각으로 나와서 죽이기~", "summary": "누군가 우각으로 나와서 죽이기 위해 유인하는 상황이다.", "title": "우각 유인으로 적 죽이기 작전!"}, {"event": {"start_sec": 5015, "end_sec": 5035, "peak_sec": 5021, "peak_z_score": 11.137967495635609, "peak_count": 4}, "evidence": "또 돌아 | 죄송함다 | 둥글게 둥글게 | 은뽀님이 우각으로만 싸우네 | 근접은 사실 그치이", "summary": "누군가 실수로 돌아 죄송하다고 하며 둥글게 둥글게 움직이던 은뽀님이 우각으로만 싸우는 상황을 지적한다.", "title": "은뽀님 우각 근접전 실수 연발!"}, {"event": {"start_sec": 5118, "end_sec": 5127, "peak_sec": 5120, "peak_z_score": 8.543371527242844, "peak_count": 2}, "evidence": "이건 홈런인데 ㅋㅋ | 홈런ㅋㅋ", "summary": "누군가 홈런을 쳤는데 그걸 재미있게 반응하며 ㅋㅋ 웃고 있다.", "title": "홈런 터진 순간 대박 ㅋㅋㅋ"}, {"event": {"start_sec": 5152, "end_sec": 5164, "peak_sec": 5154, "peak_z_score": 11.841651329465424, "peak_count": 4}, "evidence": "SR크랙 | 총 ㅋㅋ | 교체혈전 가나?", "summary": "SR크랙이 터지며 총을 맞은 듯한 상황에 교체혈전으로 가는지 묻는 반응이 나왔다.", "title": "SR크랙에 총 맞고 교체혈전 위기?"}, {"event": {"start_sec": 5244, "end_sec": 5265, "peak_sec": 5251, "peak_z_score": 11.744802662515934, "peak_count": 4}, "evidence": "300퍼센트 | 300퍼나? | 300%면 개높네 | 무려 3배 ㄷㄷ | 실력300%", "summary": "누군가 실력을 300퍼센트로 높이는 광고나 쇼츠가 갑자기 등장해 시청자들이 놀라며 웃고 사라고 추천한다.", "title": "실력 300% 폭발 광고에 ㄷㄷ 폭풍 반응"}, {"event": {"start_sec": 5416, "end_sec": 5429, "peak_sec": 5422, "peak_z_score": 9.784058880622199, "peak_count": 4}, "evidence": "베릴 ㄷㄷ | 에임은 좋으시네 | 난지님은 되게 공격적이네 | sr은..좀 | ㅈ됐다", "summary": "베릴의 좋은 에임과 난지님의 공격적인 플레이로 sr이 위기에 처해 ㅈ됐다.", "title": "베릴 에임 ㄷㄷ, 난지 공격으로 sr 위기!"}, {"event": {"start_sec": 5652, "end_sec": 5690, "peak_sec": 5666, "peak_z_score": 9.280614462798823, "peak_count": 2}, "evidence": "95살 | 늙푸 | 아조씨 | 31살 | 11살 차이", "summary": "누군가 95살이나 늙푸라고 놀리며 아조씨라고 부르자 31살이라고 밝히며 11살 차이라고 받아치는 상황.", "title": "95살 아조씨 놀림에 31살 반박 터뜨려!"}, {"event": {"start_sec": 6602, "end_sec": 6621, "peak_sec": 6606, "peak_z_score": 29.021290554260244, "peak_count": 2}, "evidence": "갈길이 멀구만 | 배그왕뉴비시네 | 그와중에 먹방 | 배그 밥먹는 게임", "summary": "배그 초보인 은뿌님이 게임 중 밥을 먹으며 제대로 플레이하지 못해 시청자들이 놀리며 먹방이라고 리액트한다.", "title": "은뿌님 배그 뉴비 먹방에 폭소 터짐"}, {"event": {"start_sec": 6628, "end_sec": 6640, "peak_sec": 6635, "peak_z_score": 10.759181157044662, "peak_count": 2}, "evidence": "빈민가 ㅋㅋ | 파밍 | 부동산 투자 | 토크나 밥시간", "summary": "파밍과 부동산 투자가 끝나 빈민가 상황에서 토크나 밥시간으로 넘어갔다.", "title": "빈민가 파밍·부동산 투자 후 밥시간 돌입"}, {"event": {"start_sec": 6646, "end_sec": 6664, "peak_sec": 6651, "peak_z_score": 10.76589043561507, "peak_count": 2}, "evidence": "강남 ㅋㅋ | 강남역에서 나와 | 집안에서 길을 잃으셨어? | 강북은 빈민가라는건갘ㅋㅋ | 강남으로 빨리 오라는 ㅋㅋ", "summary": "누군가 강북 집안에서 길을 잃고 \"강남역에서 나와 아파트로 와야지\" 하며 강남으로 빨리 오라는 놀림을 받음.", "title": "집안 길치 강남행 소환 ㅋㅋㅋ"}, {"event": {"start_sec": 6857, "end_sec": 6901, "peak_sec": 6866, "peak_z_score": 35.797764444556165, "peak_count": 4}, "evidence": "블루존 유탄 발사기 | 방프리야 | 유탄극혐 | 실내 존버", "summary": "적 전문가들이 블루존 유탄 발사기로 방프리한 좁은 집에 유탄을 집중 발사해 실내 존버를 위협한다.", "title": "블루존 유탄으로 좁은집 방프리 위기!"}, {"event": {"start_sec": 6906, "end_sec": 6919, "peak_sec": 6912, "peak_z_score": 9.655372655596311, "peak_count": 1}, "evidence": "집에 붙기 전에 죽여야 한다 | 은뿌님 총 들어오는데 | 캠보는데 깜짝 깜짝 놀라시는데 | 흐쟁이 어화둥둥이", "summary": "은뿌님이 총 들고 들어오는데 캠 보며 깜짝 놀라 공포게임처럼 반응해 흐쟁이 어화둥둥이로 넘어가려 함.", "title": "은뿌님 총 등장에 깜짝 놀라 공포 분위기 폭발"}, {"event": {"start_sec": 7449, "end_sec": 7467, "peak_sec": 7451, "peak_z_score": 9.306123662147444, "peak_count": 1}, "evidence": "버려짐 ㅋㅋ | 여자들만 모이네 | 청일점은 혼자여", "summary": "청일점이 버려져 여자들만 모인 상황이 됐다.", "title": "청일점 버려지고 여자들만 남음 ㅋㅋ"}, {"event": {"start_sec": 7524, "end_sec": 7530, "peak_sec": 7524, "peak_z_score": 12.434298282703548, "peak_count": 1}, "evidence": "", "summary": "", "title": ""}, {"event": {"start_sec": 7541, "end_sec": 7556, "peak_sec": 7547, "peak_z_score": 20.76759653344502, "peak_count": 1}, "evidence": "어우 | 구와악 | 총알 마사지", "summary": "누군가 총알 마사지를 받아 어우 구와악 소리를 내며 고통스러워하고 있다.", "title": "총알 마사지 고통에 구와악 비명 터짐"}, {"event": {"start_sec": 7591, "end_sec": 7650, "peak_sec": 7606, "peak_z_score": 210.94465075726538, "peak_count": 2}, "evidence": "ㄲㅂ | 푸린 MMR | 트레이드 | 은뽀 | 은뿌님", "summary": "푸린 MMR이 높아 트레이드를 시도했으나 백업이 바로 와서 은뽀라 불리는 은뿌님이 메딕하러 붙었다.", "title": "푸린 MMR 트레이드 백업 은뽀 메딕 상황"}, {"event": {"start_sec": 7702, "end_sec": 7721, "peak_sec": 7704, "peak_z_score": 18.018463083424326, "peak_count": 1}, "evidence": "요 ㅋㅋ | 다가져~ | yo~", "summary": "누군가 \"요 ㅋㅋ\" 하며 웃다가 \"다가져~ yo~\"라고 부르며 다가오게 유도한다.", "title": "웃으며 다가오라 부르는 장난기 가득한 순간"}, {"event": {"start_sec": 7731, "end_sec": 7758, "peak_sec": 7749, "peak_z_score": 26.8921184191464, "peak_count": 1}, "evidence": "우리 은뿌님 | 구상이나 연막탄 | 구하는 게 아직 어색하신듯 | ㅋㅋ | ㄲㅂ", "summary": "은뿌님이 구상이나 연막탄을 구하는 게 아직 어색하다며 시청자들이 웃으며 반응 중이다.", "title": "은뿌님 연막탄 구하기 어색 웃음 터짐"}, {"event": {"start_sec": 7773, "end_sec": 7797, "peak_sec": 7786, "peak_z_score": 38.82166999037241, "peak_count": 1}, "evidence": "골아픈 원이네 | 방과후 학교 | 학교 이제핫플 아니라서 ㅋㅋ", "summary": "골아픈 원이 학교 방과후 활동을 하며 이제 핫플이 아니라고 농담한다.", "title": "골아픈 원의 방과후 학교 핫플 논쟁"}, {"event": {"start_sec": 7805, "end_sec": 7812, "peak_sec": 7805, "peak_z_score": 17.624906647626783, "peak_count": 1}, "evidence": "내 소원 | 학교짱 | ㄷㄷ", "summary": "누군가 학교짱이 되는 걸 소원으로 삼아 ㄷㄷ 흥분을 표현했다.", "title": "학교짱 소원에 ㄷㄷ 리액션 폭발!"}, {"event": {"start_sec": 7854, "end_sec": 7872, "peak_sec": 7865, "peak_z_score": 17.601418984645193, "peak_count": 1}, "evidence": "학교가 맛있긴해 | 은뿌님 총알은 잘 구하심 | 총알수집 개빠름 | 학교 너프 먹음", "summary": "은뿌님이 총알수집 개빠름으로 평균 250발~350발 모으는 가운데 학교가 너프 먹음.", "title": "은뿌님 총알수집 신속함 속 학교 너프"}, {"event": {"start_sec": 7961, "end_sec": 7975, "peak_sec": 7966, "peak_z_score": 29.184590039610974, "peak_count": 1}, "evidence": "m열고 | 우클릭핑해놓고 | 배그에서 | 그런 기능 없긴 했어", "summary": "배그에서 m을 열고 우클릭핑으로 찾으려 했으나 그런 기능이 없다는 대화가 오감.", "title": "배그서 우클릭핑 기능 없어 실망"}, {"event": {"start_sec": 8022, "end_sec": 8034, "peak_sec": 8026, "peak_z_score": 27.33896960564275, "peak_count": 1}, "evidence": "창가에 | 다 바글거리네 | 낙차때문에 | 안맞았나", "summary": "창가에 다 바글거리는데 낙차 때문에 안 맞았다.", "title": "창가 바글거리다 낙차로 실패!"}, {"event": {"start_sec": 8091, "end_sec": 8102, "peak_sec": 8092, "peak_z_score": 48.76375674894028, "peak_count": 1}, "evidence": "뚜벅초들 | 웁니다 | 여기도 있네", "summary": "뚜벅초들이 여기도 있다는 사실에 웁니다 반응이 나왔다.", "title": "뚜벅초들 여기도 발견! 웁니다 터짐"}, {"event": {"start_sec": 8125, "end_sec": 8164, "peak_sec": 8142, "peak_z_score": 65.10982184120132, "peak_count": 1}, "evidence": "도트가 급해 | 응처장 | 은뽀 | 은뿌? | 장전해주세요", "summary": "도트가 급해진 상황에서 응처장과 은뽀 은뿌 목소리 구별이 안 되고 장전을 요청한다.", "title": "도트 급해 목소리 구별 못해 장전 요청 피크"}, {"event": {"start_sec": 8178, "end_sec": 8223, "peak_sec": 8199, "peak_z_score": 74.3553119602736, "peak_count": 1}, "evidence": "블루존유탄발사기 | 개후지니까 | 당해봤는데 개좋던디 | 뚜벅이", "summary": "블루존유탄발사기를 뚜벅이로 당한 사람이 개좋다고 느끼며 이전에 후지라 쓰지 말라 했던 무기를 두고 의견이 갈린다.", "title": "블루존유탄에 뚜벅이 당해 '개좋다' 리액션 폭발"}, {"event": {"start_sec": 8231, "end_sec": 8250, "peak_sec": 8240, "peak_z_score": 38.29459569113192, "peak_count": 1}, "evidence": "연막 유탄 | 자리 뺏는것 | 여기 팀이 죽었는걸", "summary": "연막 유탄으로 자리 뺏는 바람에 여기 팀이 죽었다.", "title": "연막 유탄 자리 뺏기로 팀 전멸"}, {"event": {"start_sec": 8290, "end_sec": 8301, "peak_sec": 8290, "peak_z_score": 31.168193428165836, "peak_count": 2}, "evidence": "고인 사람들 | ㄲㅂ | 저친구들 자신감 넘치는데", "summary": "고인 사람들만 쓰는 ㄲㅂ을 저친구들이 자신감 넘치게 써서 이유를 추측 중이다.", "title": "고인들 전용 ㄲㅂ에 자신만만한 저친구들 등장"}, {"event": {"start_sec": 8310, "end_sec": 8329, "peak_sec": 8311, "peak_z_score": 21.72194211743869, "peak_count": 1}, "evidence": "!멤버 | 치카 | 아구이뽀 | 왈도쿤 | 난지", "summary": "!멤버 명령으로 치카 아구이뽀 왈도쿤 난지 텐텐 은뿌 멤버 목록이 표시됐다.", "title": "멤버 목록 공개! 치카·아구이뽀 등장"}, {"event": {"start_sec": 8342, "end_sec": 8350, "peak_sec": 8342, "peak_z_score": 21.436548096894658, "peak_count": 1}, "evidence": "ㄴㅇㅅ", "summary": "누군가 ㄴㅇㅅ로 짧게 반응하며 상황을 표현했다.", "title": "ㄴㅇㅅ 반응 터진 순간"}, {"event": {"start_sec": 8378, "end_sec": 8393, "peak_sec": 8381, "peak_z_score": 52.773253927172355, "peak_count": 2}, "evidence": "ㄲㅂ | ㄲㅂ 너무 당당했다 | ㄲㅂ", "summary": "ㄲㅂ이 너무 당당하게 행동해 모두가 반복적으로 언급하며 놀랐다.", "title": "ㄲㅂ의 당당함에 채팅 폭발!"}, {"event": {"start_sec": 8396, "end_sec": 8422, "peak_sec": 8413, "peak_z_score": 29.980280947089565, "peak_count": 1}, "evidence": "그래도 말 잘듣는데 | 7번 같은팀이었음 | 로족얘들이 올라가서 붙은거", "summary": "7번이 같은 팀이었는데 로족 얘들이 올라가서 붙었음에도 말 잘 듣는 상황.", "title": "7번 동료인데 로족이 올라 붙어도 순종적!"}, {"event": {"start_sec": 8478, "end_sec": 8495, "peak_sec": 8481, "peak_z_score": 24.89208148963155, "peak_count": 1}, "evidence": "팀보니 | 우승가능성 | 제로는 아니네 | ㄲㅂ | 아쉬웠네요", "summary": "팀보니가 우승 가능성이 제로는 아니었으나 결국 아쉬운 결과로 끝나 ㄲㅂ 리액션이 나왔다.", "title": "팀보니 우승 문턱 스쳤지만 아쉬운 패배"}, {"event": {"start_sec": 8515, "end_sec": 8587, "peak_sec": 8522, "peak_z_score": 33.0246380930719, "peak_count": 2}, "evidence": "텐플러스텐텐텐 | 텐텐님 | 팀 정해진거임 ?? | 네 팀 확정 | 황금 풍뎅이", "summary": "텐플러스텐텐텐(텐텐님) 팀이 '황금 풍뎅이'로 확정되며 시청자들이 환호하고 있다.", "title": "텐텐님 '황금 풍뎅이' 팀 확정 환호!"}, {"event": {"start_sec": 8619, "end_sec": 8628, "peak_sec": 8623, "peak_z_score": 12.125292441617614, "peak_count": 1}, "evidence": "오우 | 치일뻔 | ㅋㅋ", "summary": "\"치일뻔\"해서 \"오우\" 하며 \"ㅋㅋ\" 웃는 상황.", "title": "치일 뻔한 순간에 오우ㅋㅋ 리액션 폭발"}, {"event": {"start_sec": 8785, "end_sec": 8808, "peak_sec": 8787, "peak_z_score": 14.303423536482109, "peak_count": 1}, "evidence": "ㅋㅋ 개웃겨 | 군필인가? | 군필여고생이신가 | 군필여고생이셔?", "summary": "누군가의 행동이 \"ㅋㅋ 개웃겨\"라고 할 정도로 재미있어 \"군필여고생\" 농담이 오갔다.", "title": "여고생 군필자 농담 터진 순간"}, {"event": {"start_sec": 8785, "end_sec": 8818, "peak_sec": 8801, "peak_z_score": 18.072725907730074, "peak_count": 1}, "evidence": "군필인가? | 군필여고생이신가 | 군필여고생이셔? | 그게 무슨 소리니 푸린푸린아", "summary": "누군가 여고생에게 군필 의심 농담을 던지자 푸린푸린아가 \"그게 무슨 소리니\"라고 당황하며 웃음 터짐.", "title": "여고생 군필 의심 농담에 폭소 터진 순간"}, {"event": {"start_sec": 8910, "end_sec": 8919, "peak_sec": 8914, "peak_z_score": 10.713863741109293, "peak_count": 1}, "evidence": "", "summary": "", "title": ""}, {"event": {"start_sec": 8943, "end_sec": 9014, "peak_sec": 8965, "peak_z_score": 41.69114823762775, "peak_count": 3}, "evidence": "블루님 헬프 | 블하 | 블루님 구해줘 | 우승팀이구나 | 약팀이에요", "summary": "약팀인 척하며 블루님에게 구원을 요청하고 블하로 장난치며 연습 분위기를 띄운다.", "title": "약팀 연습생들, 블루님 구원요청 폭발!"}, {"event": {"start_sec": 9297, "end_sec": 9312, "peak_sec": 9301, "peak_z_score": 15.440670742579181, "peak_count": 2}, "evidence": "무섭뉴 | 아고 | 아이고 | ㄲㅂ", "summary": "무서운 상황에 \"무섭뉴\"와 \"아이고\" 하며 놀라고 \"ㄲㅂ\" 연발로 공포에 질렸다.", "title": "무서움 폭발! ㄲㅂ 연타 공포의 순간"}, {"event": {"start_sec": 9364, "end_sec": 9379, "peak_sec": 9371, "peak_z_score": 10.27997244318686, "peak_count": 2}, "evidence": "ㅊㅊ | 감사합니다 행님들 | 방위전이 아니었어서 | 이해가 가셨으려나 ㅋㅋ", "summary": "방위전이 아니었음을 설명하며 감사 인사와 함께 ㅊㅊ로 마무리했다.", "title": "방위전 아닌 상황 이해 부탁하며 퇴장 인사"}, {"event": {"start_sec": 9961, "end_sec": 9991, "peak_sec": 9973, "peak_z_score": 44.44152075861317, "peak_count": 1}, "evidence": "ㄴㅇㅅ | 굿 | 1단 은뿌를 던지다의 올바른 사례", "summary": "누군가 \"1단 은뿌를 던지다의 올바른 사례\"를 보여주며 \"ㄴㅇㅅ\"와 \"굿\" 반응을 받았다.", "title": "1단 은뿌 던지기 올바른 사례 성공!"}, {"event": {"start_sec": 10021, "end_sec": 10030, "peak_sec": 10021, "peak_z_score": 35.20097913940084, "peak_count": 1}, "evidence": "블루존이 하얘졌네", "summary": "블루존이 하얘지는 일이 벌어졌다.", "title": "블루존 하얀색 변색 발생!"}, {"event": {"start_sec": 10076, "end_sec": 10135, "peak_sec": 10076, "peak_z_score": 22.166490379356173, "peak_count": 1}, "evidence": "다른팀한테 죽었네 | ㄴㅇㅅ | ㄲㅂ | 그래도 닦은게 어디야 | 발전했다", "summary": "다른팀한테 죽었지만 적을 닦은 게 있어서 ㄲㅂ 하며 발전했다고 평가한다.", "title": "다른팀에 당했지만 성장 인정! ㄲㅂ 칭찬 터짐"}, {"event": {"start_sec": 10147, "end_sec": 10159, "peak_sec": 10147, "peak_z_score": 54.696125267145206, "peak_count": 1}, "evidence": "슈류탄 | 안던진게 | 장족의 발전 | 킹능성", "summary": "슈류탄을 안 던진 게 장족의 발전으로 평가되며 살짝 킹능성을 보일지도 모른다.", "title": "슈류탄 참은 게 장족의 발전? 킹능성 예고"}, {"event": {"start_sec": 10176, "end_sec": 10271, "peak_sec": 10211, "peak_z_score": 321.40543797099673, "peak_count": 3}, "evidence": "샷건 장전 안되어있어서 | ㄴㅇㅅ | 푸성근이 | 푸버지 파이팅 | 블루칩", "summary": "샷건 장전 안되어있어 접힌 실수로 웃음바다가 된 가운데 푸성근이와 푸버지 팀이 발전하며 응원받고 있다.", "title": "샷건 장전 실패로 푸성근 접히고 응원 폭발!"}, {"event": {"start_sec": 10276, "end_sec": 10302, "peak_sec": 10276, "peak_z_score": 35.82038456066931, "peak_count": 1}, "evidence": "ㅋㅋ | 다 | 귀여우시다", "summary": "다들 귀여워서 ㅋㅋ 웃으며 칭찬하는 반응이 나왔다.", "title": "모두 귀여워서 웃음 터진 순간"}, {"event": {"start_sec": 10305, "end_sec": 10390, "peak_sec": 10305, "peak_z_score": 36.327021386091, "peak_count": 1}, "evidence": "푸린님 팀장인가요? | 1티어됨 | 푸코치 | 1010님 피가", "summary": "푸린님이 팀장은 아니지만 1티어로 올라 사실상 푸코치가 됐고 1010님 피가 언급되며 팀 상황이 유쾌하게 전개됐다.", "title": "푸린 1티어 코치 등극에 1010 피 터짐"}, {"event": {"start_sec": 10399, "end_sec": 10411, "peak_sec": 10405, "peak_z_score": 16.283672740085045, "peak_count": 1}, "evidence": "당황하지~말아오", "summary": "누군가 당황하지 말라는 위로의 말을 건넸다.", "title": "당황 말라는 다급한 위로 소리"}, {"event": {"start_sec": 10427, "end_sec": 10455, "peak_sec": 10433, "peak_z_score": 23.625742170440795, "peak_count": 2}, "evidence": "살아남았다 | 드리프트 | 팀킬 | 차가 카트라이더하는데", "summary": "살아남았지만 차가 드리프트를 하다 팀킬로 미쳐버리는 꿀잼 상황.", "title": "드리프트 팀킬로 폭소 터진 카트라이더 레이스"}, {"event": {"start_sec": 10427, "end_sec": 10473, "peak_sec": 10464, "peak_z_score": 12.44861449966278, "peak_count": 1}, "evidence": "드리프트 ㅋㅋ | 팀킬ㅋㅋ | 카트라이더임 | ㄲㅂ", "summary": "카트라이더에서 드리프트하며 살아남았으나 팀킬하고 자살 직전까지 갔다.", "title": "카트라이더 드리프트 팀킬 대참사ㅋㅋ"}, {"event": {"start_sec": 11101, "end_sec": 11109, "peak_sec": 11103, "peak_z_score": 16.48891726075124, "peak_count": 2}, "evidence": "드래그 | 탭 해서 넣으면 | 후반부 | 엄폐 | 해서 먹으면 되요", "summary": "후반부에 엄폐가 없을 경우 드래그나 탭 해서 넣으면 먹을 수 있다고 조언한다.", "title": "후반부 엄폐 부족 시 드래그 탭 공략법"}, {"event": {"start_sec": 11118, "end_sec": 11124, "peak_sec": 11119, "peak_z_score": 9.82909415062985, "peak_count": 1}, "evidence": "옹 | 굳~ | -----", "summary": "누군가 \"옹\" 소리를 내며 \"굳~\" 인사를 나누고 구분선을 그었다.", "title": "방송 시작 인사와 반응 터짐"}, {"event": {"start_sec": 11170, "end_sec": 11174, "peak_sec": 11170, "peak_z_score": 8.424044673527835, "peak_count": 1}, "evidence": "방패좋죵", "summary": "방패가 좋다는 반응이 나왔다.", "title": "방패 좋다는 감탄 터짐"}, {"event": {"start_sec": 11199, "end_sec": 11230, "peak_sec": 11200, "peak_z_score": 13.760508095851558, "peak_count": 1}, "evidence": "방금 소리머임 | 귀여운 효과으미 | 팀 잘짜인거같은데 | 살려줘중 ㅋㅋ | 공포게임 후열", "summary": "공포게임에서 귀여운 효과음과 소리가 나며 잘 짜인 팀이 살려줘중 상황을 겪고 후열 팀이 더 기대된다.", "title": "공포게임 팀전, 귀여운 소리와 살려줘 긴장감!"}, {"event": {"start_sec": 11242, "end_sec": 11247, "peak_sec": 11242, "peak_z_score": 9.858532244549258, "peak_count": 1}, "evidence": "좋아요~", "summary": "누군가 \"좋아요~\"라고 긍정적인 반응을 보였다.", "title": "좋아요 반응 터짐"}, {"event": {"start_sec": 11253, "end_sec": 11306, "peak_sec": 11287, "peak_z_score": 80.69112649661706, "peak_count": 2}, "evidence": "교수님의 내구도실험 | 미르시치님 오셔따 | 범인이다 | 미하 | 어우죽을뻔", "summary": "미르시치님이 등장하며 교수님의 내구도실험 중 범인으로 지목되고 미하를 외치며 죽을 뻔한 상황이 벌어짐.", "title": "미르시치 등장에 교수 내구실험 폭발! 범인 미하?"}, {"event": {"start_sec": 11322, "end_sec": 11358, "peak_sec": 11340, "peak_z_score": 26.86339900578899, "peak_count": 2}, "evidence": "범인 왔네 | 차량 이동중에 드링크 진통제 아드레날린 붕대만 가능합니다 | 해설진의 개입에 분노할뿐", "summary": "범인이 등장하고 차량 이동 중 아이템 제한 상황에서 해설진 개입에 분노가 터졌다.", "title": "범인 등장에 해설진 개입으로 분노 폭발!"}, {"event": {"start_sec": 11373, "end_sec": 11379, "peak_sec": 11374, "peak_z_score": 11.418286884847335, "peak_count": 1}, "evidence": "푸린 | 큰일났을 팀 | 미르다요 | 석고대죄", "summary": "푸린이 없었으면 큰일 날 뻔한 팀을 구했는데 미르다요는 석고대죄를 해야 한다.", "title": "푸린 덕에 위기 탈출, 미르다요 사죄 위기"}, {"event": {"start_sec": 11403, "end_sec": 11407, "peak_sec": 11403, "peak_z_score": 9.42800082532283, "peak_count": 2}, "evidence": "다른 팀도 힘들구먼 | 그냥 머 이런저런 | 나쁘지 않을지도", "summary": "다른 팀도 힘들어 보이지만 그냥 이런저런 나쁘지 않을지도 모른다는 반응이다.", "title": "다른 팀 고생 중, 괜찮을지도?"}, {"event": {"start_sec": 11577, "end_sec": 11600, "peak_sec": 11582, "peak_z_score": 14.38105701958051, "peak_count": 2}, "evidence": "쓰레기 | 좋은거야 먹어(벗어) | 내놔~ | 분대장님을 위해 희생한다 | 마인드좋다", "summary": "누군가 '쓰레기'라고 불리는 것을 '좋은거야 먹어(벗어)' 하며 내놓으라고 요구하고, 분대장님을 위해 희생하며 마인드 좋다고 응원하는 상황.", "title": "분대장 위해 쓰레기 희생 먹방 도전!"}, {"event": {"start_sec": 11866, "end_sec": 11890, "peak_sec": 11872, "peak_z_score": 10.363522023267162, "peak_count": 1}, "evidence": "ㄲㅂ | 간다 | 감자엔딩 | 언덕위에서 꿀빨았네 | 막판 ㄱㄱ", "summary": "언덕 위에서 꿀빨았네 하며 ㄲㅂ 반복하며 막판에 간다는 리액션으로 감자엔딩 맞음.", "title": "언덕 꿀빨고 막판 ㄲㅂ 감자엔딩!"}, {"event": {"start_sec": 12086, "end_sec": 12102, "peak_sec": 12094, "peak_z_score": 10.279466213680083, "peak_count": 2}, "evidence": "남아라 선언 | 남아.. | 싸움이 강해지고 싶은자 나에게로 | 푸크로드", "summary": "누군가 \"남아라 선언\"하며 \"싸움이 강해지고 싶은자 나에게로\" 오라고 유도하고 푸크로드를 언급하며 남아있으라고 재촉하는 상황.", "title": "남아라 선언으로 싸움 유도하는 피크 순간"}, {"event": {"start_sec": 12547, "end_sec": 12552, "peak_sec": 12548, "peak_z_score": 8.582670217354044, "peak_count": 1}, "evidence": "분대장은..", "summary": "분대장이 등장하거나 언급되며 시청자들이 반응하는 상황이다.", "title": "분대장 등장에 채팅 폭발!"}, {"event": {"start_sec": 12579, "end_sec": 12599, "peak_sec": 12587, "peak_z_score": 11.121317221417783, "peak_count": 2}, "evidence": "와우!! | 맞말추~ | 전멸수준의 위기지 | ㅋㅋ 맞긴 해.", "summary": "팀이 전멸수준의 위기에 처해 맞말추기 상황이 벌어졌고 모두가 동의하며 웃었다.", "title": "전멸 위기 탈출! 맞말추 성공 순간"}, {"event": {"start_sec": 12652, "end_sec": 12671, "peak_sec": 12660, "peak_z_score": 11.954444183822897, "peak_count": 2}, "evidence": "갓토나 절대 안뒤집어지지 | 주차만 잘하는 타입 | 라고 말하자 마자;;; | ㅈ됬는데", "summary": "갓토나가 절대 안 뒤집어진다고 말하자 마자 실제로 뒤집혀서 ㅈ됐다고 인정하는 상황.", "title": "갓토나 자랑하자마자 즉시 뒤집힘 ㅈ됨"}, {"event": {"start_sec": 12958, "end_sec": 12981, "peak_sec": 12965, "peak_z_score": 10.627874251110608, "peak_count": 1}, "evidence": "산타인가? | 저거 뭐지 ㅋㅋ | 보급인가 | 타고 날라는건가?", "summary": "누군가 산타처럼 보이는 게 하늘을 타고 날아 보급인지 뭔지 모를 걸 나타나 에임 논란이 일었다.", "title": "산타? 날아다니는 미확인 보급 등장!"}, {"event": {"start_sec": 13292, "end_sec": 13304, "peak_sec": 13296, "peak_z_score": 10.404192528177669, "peak_count": 1}, "evidence": "택시 지붕에 걸리네 | 은신 뭔데 | 택싴ㅋㅋ", "summary": "택시 지붕에 무언가가 걸려 은신이 의심되는 웃긴 상황이 벌어졌다.", "title": "택시 지붕에 걸린 은신 미스터리ㅋㅋ"}, {"event": {"start_sec": 13622, "end_sec": 13670, "peak_sec": 13630, "peak_z_score": 51.1932751080841, "peak_count": 7}, "evidence": "ㄴㅇㅅ | 치킨!! | 수류탄 엔딩 | 하드캐리 | 이게되네", "summary": "수류탄으로 하드캐리하며 막판에 치킨을 따냈다.", "title": "수류탄 캐리로 치킨 따는 기적의 엔딩!"}, {"event": {"start_sec": 13672, "end_sec": 13714, "peak_sec": 13695, "peak_z_score": 29.139194422091578, "peak_count": 3}, "evidence": "수고하셨습니다 | 고생하셨습니다 | 푸린 | 배그유치원 | 베그도 잘해", "summary": "푸린이 배그유치원 같은 팀과 함께 재미있는 게임을 마치고 수고 인사를 받음.", "title": "푸린 배그팀의 즐거운 유치원급 경기 마무리!"}, {"event": {"start_sec": 13719, "end_sec": 13767, "peak_sec": 13734, "peak_z_score": 20.23863732403629, "peak_count": 2}, "evidence": "배그유치원 ㅋㅋ | 블루 오긴했었어 ㅋㅋ | 곰파 가르쳐주면 강지님한테 이른다고 하죠", "summary": "배그유치원 수준의 약팀이 블루와 미르가 왔음에도 불구하고 의지로 버티며 지게차 상황에서 화이팅 중이다.", "title": "배그유치원 약팀, 블루 미르 방문에도 화이팅!"}, {"event": {"start_sec": 14001, "end_sec": 14033, "peak_sec": 14010, "peak_z_score": 23.811382644748143, "peak_count": 4}, "evidence": "푸바 | 좋은 꿈꾸시고 좋은 날만 있으시길 바랍니다! | 내일 그럼 6시에 오는거? | 재미있었다", "summary": "푸바를 반복하며 방송 종료를 축하하고 내일 6시 재방문을 약속하며 흩어지는 상황이다.", "title": "푸바 연발 속 푸른 작별 인사와 내일 6시 약속"}, {"event": {"start_sec": 14220, "end_sec": 14230, "peak_sec": 14230, "peak_z_score": 8.04237722930565, "peak_count": 5}, "evidence": "ㅔㅔ | 푸바 | 푸바푸바 | 좋은 꿈 꾸세요", "summary": "ㅔㅔ와 푸바 소리를 내며 좋은 꿈 꾸세요로 인사하며 방송이 끝나갈 때의 흥겨운 분위기.", "title": "푸바 울리는 퇴장 인사 피크!"}]}